{"DocumentConnection":{"type":"DocumentConnection","resolveType":"multiCollectionDocumentList","collections":["home_en","home_si","home_ta","about_en","about_si","about_ta"]},"Node":{"type":"Node","resolveType":"nodeDocument"},"DocumentNode":{"type":"DocumentNode","resolveType":"multiCollectionDocument","createDocument":"create","updateDocument":"update"},"Home_en":{"type":"Home_en","resolveType":"collectionDocument","collection":"home_en","createHome_en":"create","updateHome_en":"update"},"Home_enConnection":{"type":"Home_enConnection","resolveType":"collectionDocumentList","collection":"home_en"},"Home_si":{"type":"Home_si","resolveType":"collectionDocument","collection":"home_si","createHome_si":"create","updateHome_si":"update"},"Home_siConnection":{"type":"Home_siConnection","resolveType":"collectionDocumentList","collection":"home_si"},"Home_ta":{"type":"Home_ta","resolveType":"collectionDocument","collection":"home_ta","createHome_ta":"create","updateHome_ta":"update"},"Home_taConnection":{"type":"Home_taConnection","resolveType":"collectionDocumentList","collection":"home_ta"},"About_en":{"type":"About_en","resolveType":"collectionDocument","collection":"about_en","createAbout_en":"create","updateAbout_en":"update"},"About_enConnection":{"type":"About_enConnection","resolveType":"collectionDocumentList","collection":"about_en"},"About_si":{"type":"About_si","resolveType":"collectionDocument","collection":"about_si","createAbout_si":"create","updateAbout_si":"update"},"About_siConnection":{"type":"About_siConnection","resolveType":"collectionDocumentList","collection":"about_si"},"About_ta":{"type":"About_ta","resolveType":"collectionDocument","collection":"about_ta","createAbout_ta":"create","updateAbout_ta":"update"},"About_taConnection":{"type":"About_taConnection","resolveType":"collectionDocumentList","collection":"about_ta"}}