{"DocumentConnection":{"type":"DocumentConnection","resolveType":"multiCollectionDocumentList","collections":["home_en","home_si","home_ta","about_en","about_si","about_ta","departments_en","departments_si","departments_ta","membership_en","membership_si","membership_ta","publications_en","publications_si","publications_ta","events_en","events_si","events_ta","gallery_en","gallery_si","gallery_ta"]},"Node":{"type":"Node","resolveType":"nodeDocument"},"DocumentNode":{"type":"DocumentNode","resolveType":"multiCollectionDocument","createDocument":"create","updateDocument":"update"},"Home_en":{"type":"Home_en","resolveType":"collectionDocument","collection":"home_en","createHome_en":"create","updateHome_en":"update"},"Home_enConnection":{"type":"Home_enConnection","resolveType":"collectionDocumentList","collection":"home_en"},"Home_si":{"type":"Home_si","resolveType":"collectionDocument","collection":"home_si","createHome_si":"create","updateHome_si":"update"},"Home_siConnection":{"type":"Home_siConnection","resolveType":"collectionDocumentList","collection":"home_si"},"Home_ta":{"type":"Home_ta","resolveType":"collectionDocument","collection":"home_ta","createHome_ta":"create","updateHome_ta":"update"},"Home_taConnection":{"type":"Home_taConnection","resolveType":"collectionDocumentList","collection":"home_ta"},"About_en":{"type":"About_en","resolveType":"collectionDocument","collection":"about_en","createAbout_en":"create","updateAbout_en":"update"},"About_enConnection":{"type":"About_enConnection","resolveType":"collectionDocumentList","collection":"about_en"},"About_si":{"type":"About_si","resolveType":"collectionDocument","collection":"about_si","createAbout_si":"create","updateAbout_si":"update"},"About_siConnection":{"type":"About_siConnection","resolveType":"collectionDocumentList","collection":"about_si"},"About_ta":{"type":"About_ta","resolveType":"collectionDocument","collection":"about_ta","createAbout_ta":"create","updateAbout_ta":"update"},"About_taConnection":{"type":"About_taConnection","resolveType":"collectionDocumentList","collection":"about_ta"},"Departments_en":{"type":"Departments_en","resolveType":"collectionDocument","collection":"departments_en","createDepartments_en":"create","updateDepartments_en":"update"},"Departments_enConnection":{"type":"Departments_enConnection","resolveType":"collectionDocumentList","collection":"departments_en"},"Departments_si":{"type":"Departments_si","resolveType":"collectionDocument","collection":"departments_si","createDepartments_si":"create","updateDepartments_si":"update"},"Departments_siConnection":{"type":"Departments_siConnection","resolveType":"collectionDocumentList","collection":"departments_si"},"Departments_ta":{"type":"Departments_ta","resolveType":"collectionDocument","collection":"departments_ta","createDepartments_ta":"create","updateDepartments_ta":"update"},"Departments_taConnection":{"type":"Departments_taConnection","resolveType":"collectionDocumentList","collection":"departments_ta"},"Membership_en":{"type":"Membership_en","resolveType":"collectionDocument","collection":"membership_en","createMembership_en":"create","updateMembership_en":"update"},"Membership_enConnection":{"type":"Membership_enConnection","resolveType":"collectionDocumentList","collection":"membership_en"},"Membership_si":{"type":"Membership_si","resolveType":"collectionDocument","collection":"membership_si","createMembership_si":"create","updateMembership_si":"update"},"Membership_siConnection":{"type":"Membership_siConnection","resolveType":"collectionDocumentList","collection":"membership_si"},"Membership_ta":{"type":"Membership_ta","resolveType":"collectionDocument","collection":"membership_ta","createMembership_ta":"create","updateMembership_ta":"update"},"Membership_taConnection":{"type":"Membership_taConnection","resolveType":"collectionDocumentList","collection":"membership_ta"},"Publications_en":{"type":"Publications_en","resolveType":"collectionDocument","collection":"publications_en","createPublications_en":"create","updatePublications_en":"update"},"Publications_enConnection":{"type":"Publications_enConnection","resolveType":"collectionDocumentList","collection":"publications_en"},"Publications_si":{"type":"Publications_si","resolveType":"collectionDocument","collection":"publications_si","createPublications_si":"create","updatePublications_si":"update"},"Publications_siConnection":{"type":"Publications_siConnection","resolveType":"collectionDocumentList","collection":"publications_si"},"Publications_ta":{"type":"Publications_ta","resolveType":"collectionDocument","collection":"publications_ta","createPublications_ta":"create","updatePublications_ta":"update"},"Publications_taConnection":{"type":"Publications_taConnection","resolveType":"collectionDocumentList","collection":"publications_ta"},"Events_en":{"type":"Events_en","resolveType":"collectionDocument","collection":"events_en","createEvents_en":"create","updateEvents_en":"update"},"Events_enConnection":{"type":"Events_enConnection","resolveType":"collectionDocumentList","collection":"events_en"},"Events_si":{"type":"Events_si","resolveType":"collectionDocument","collection":"events_si","createEvents_si":"create","updateEvents_si":"update"},"Events_siConnection":{"type":"Events_siConnection","resolveType":"collectionDocumentList","collection":"events_si"},"Events_ta":{"type":"Events_ta","resolveType":"collectionDocument","collection":"events_ta","createEvents_ta":"create","updateEvents_ta":"update"},"Events_taConnection":{"type":"Events_taConnection","resolveType":"collectionDocumentList","collection":"events_ta"},"Gallery_en":{"type":"Gallery_en","resolveType":"collectionDocument","collection":"gallery_en","createGallery_en":"create","updateGallery_en":"update"},"Gallery_enConnection":{"type":"Gallery_enConnection","resolveType":"collectionDocumentList","collection":"gallery_en"},"Gallery_si":{"type":"Gallery_si","resolveType":"collectionDocument","collection":"gallery_si","createGallery_si":"create","updateGallery_si":"update"},"Gallery_siConnection":{"type":"Gallery_siConnection","resolveType":"collectionDocumentList","collection":"gallery_si"},"Gallery_ta":{"type":"Gallery_ta","resolveType":"collectionDocument","collection":"gallery_ta","createGallery_ta":"create","updateGallery_ta":"update"},"Gallery_taConnection":{"type":"Gallery_taConnection","resolveType":"collectionDocumentList","collection":"gallery_ta"}}